neoathena/__init__.py
neoathena/client.py
neoathena/models.py
neoathena-0.0.3.dist-info/licenses/LICENSE
neoathena-0.0.3.dist-info/METADATA
neoathena-0.0.3.dist-info/WHEEL
neoathena-0.0.3.dist-info/top_level.txt
neoathena-0.0.3.dist-info/RECORD
