Metadata-Version: 2.4
Name: neoathena
Version: 0.0.3
Summary: A Python client for the NeoAthena API
Home-page: https://github.com/raen-ai/neoathena
Author: Raen AI
Author-email: Raen AI <support@raen.ai>
License: MIT
Project-URL: Homepage, https://github.com/raen-ai/neoathena
Project-URL: Repository, https://github.com/raen-ai/neoathena.git
Project-URL: Issues, https://github.com/raen-ai/neoathena/issues
Classifier: Development Status :: 3 - Alpha
Classifier: Intended Audience :: Developers
Classifier: License :: OSI Approved :: MIT License
Classifier: Programming Language :: Python :: 3
Classifier: Programming Language :: Python :: 3.8
Classifier: Programming Language :: Python :: 3.9
Classifier: Programming Language :: Python :: 3.10
Classifier: Programming Language :: Python :: 3.11
Classifier: Programming Language :: Python :: 3.12
Requires-Python: >=3.8
License-File: LICENSE
Requires-Dist: requests>=2.25.0
Requires-Dist: typing>=3.7.4; python_version < "3.8"
Requires-Dist: pydantic==2.10.6
Requires-Dist: requests==2.32.3
Requires-Dist: black==25.1.0
Requires-Dist: langchain-core==0.3.33
Requires-Dist: bandit==1.8.2
Requires-Dist: pytest-mock==3.14.0
Requires-Dist: pytest==8.3.4
Dynamic: author
Dynamic: home-page
Dynamic: license-file
Dynamic: requires-python
